etc/msbackup/msbackup.conf
msbackup/__init__.py
msbackup/__main__.py
msbackup/archive.py
msbackup/backend.py
msbackup/backend_base.py
msbackup/backend_file.py
msbackup/backend_hg.py
msbackup/backend_kvm.py
msbackup/backend_ldap.py
msbackup/backend_mongodb.py
msbackup/backend_pg.py
msbackup/backend_sqlite.py
msbackup/backend_svn.py
msbackup/cli.py
msbackup/encrypt.py
msbackup/flock.py
msbackup/utils.py
msbackup-2.1.6.dist-info/LICENSE
msbackup-2.1.6.dist-info/METADATA
msbackup-2.1.6.dist-info/WHEEL
msbackup-2.1.6.dist-info/entry_points.txt
msbackup-2.1.6.dist-info/top_level.txt
msbackup-2.1.6.dist-info/RECORD
