Metadata-Version: 2.1
Name: msbackup
Version: 2.1.6
Summary: Generic backup utility.
Home-page: https://redmine.mousesoft.ru/projects/msbackup
Author: Aleksei Badiaev
Author-email: aleksei.badiaev@mousesoft.ru
License: MIT
Keywords: linux backup administration
Platform: UNKNOWN
Classifier: Development Status :: 5 - Production/Stable
Classifier: Intended Audience :: System Administrators
Classifier: License :: OSI Approved :: MIT License
Classifier: Natural Language :: Russian
Classifier: Operating System :: POSIX :: Linux
Classifier: Programming Language :: Python :: 3
Classifier: Topic :: System :: Archiving :: Backup
Requires-Python: >=3.5
Provides-Extra: dev
Requires-Dist: check-manifest ; extra == 'dev'
Requires-Dist: coverage ; extra == 'dev'
Requires-Dist: doc8 ; extra == 'dev'
Requires-Dist: docutils ; extra == 'dev'
Requires-Dist: flake8 ; extra == 'dev'
Requires-Dist: ipdb ; extra == 'dev'
Requires-Dist: libvirt-python ; extra == 'dev'
Requires-Dist: pep8 ; extra == 'dev'
Requires-Dist: pydocstyle ; extra == 'dev'
Requires-Dist: stdeb3 ; extra == 'dev'
Requires-Dist: twine ; extra == 'dev'
Requires-Dist: unittest-xml-reporting ; extra == 'dev'
Requires-Dist: wheel ; extra == 'dev'
Provides-Extra: kvm
Requires-Dist: libvirt-python ; extra == 'kvm'
